krakensegment/__init__.py
krakensegment/binarization.py
krakensegment/pageseg.py
krakensegment/lib/__init__.py
krakensegment/lib/exceptions.py
krakensegment/lib/log.py
krakensegment/lib/morph.py
krakensegment/lib/sl.py
krakensegment/lib/util.py
krakensegment-0.4.dist-info/LICENSE
krakensegment-0.4.dist-info/METADATA
krakensegment-0.4.dist-info/WHEEL
krakensegment-0.4.dist-info/top_level.txt
krakensegment-0.4.dist-info/RECORD
